Metadata-Version: 2.1
Name: prob-d
Version: 0.1
Summary: Binomial distributions and Gaussian distributions
Home-page: UNKNOWN
Author: Nishita Jain
License: UNKNOWN
Platform: UNKNOWN
